README.md
setup.py
tmux_helper_filetransfer/__init__.py
tmux_helper_filetransfer/__main__.py
tmux_helper_filetransfer/cli.py
tmux_helper_filetransfer.egg-info/PKG-INFO
tmux_helper_filetransfer.egg-info/SOURCES.txt
tmux_helper_filetransfer.egg-info/dependency_links.txt
tmux_helper_filetransfer.egg-info/entry_points.txt
tmux_helper_filetransfer.egg-info/top_level.txt