Metadata-Version: 2.1
Name: tmux-helper-filetransfer
Version: 0.1.0
Summary: file transfer cli utility for tmux
Home-page: https://github.com/chrahunt/tmux-helper-filetransfer
License: MIT
Platform: UNKNOWN
Classifier: Development Status :: 3 - Alpha
Classifier: License :: OSI Approved :: MIT License
Classifier: Operating System :: POSIX
Classifier: Programming Language :: Python :: 3.6
Classifier: Programming Language :: Python :: 3.7
Classifier: Topic :: Terminals
Classifier: Topic :: Terminals :: Terminal Emulators/X Terminals
Classifier: Topic :: Utilities
Requires-Python: ~=3.6
